LICENSE
MANIFEST.in
README.md
setup.py
opaquestore/__init__.py
opaquestore/cfg.py
opaquestore/client.py
opaquestore.egg-info/PKG-INFO
opaquestore.egg-info/SOURCES.txt
opaquestore.egg-info/dependency_links.txt
opaquestore.egg-info/entry_points.txt
opaquestore.egg-info/requires.txt
opaquestore.egg-info/top_level.txt