Metadata-Version: 2.1
Name: opaquestore
Version: 0.3.0
Summary: Simple Online secret-storage based on the OPAQUE protocol
Home-page: https://github.com/stef/opaque-store/
Author: Stefan Marsiske
Author-email: opaque@ctrlc.hu
License: GPLv3
Classifier: Development Status :: 4 - Beta
Classifier: License :: OSI Approved :: GNU General Public License v3 or later (GPLv3+)
Classifier: Topic :: Security :: Cryptography
Classifier: Topic :: Security
License-File: LICENSE
Requires-Dist: pysodium
Requires-Dist: SecureString
Requires-Dist: opaque
Requires-Dist: zxcvbn-python
Requires-Dist: pyoprf
